odoo/addons/energy_communities_crm/README.md
odoo/addons/energy_communities_crm/__init__.py
odoo/addons/energy_communities_crm/__manifest__.py
odoo/addons/energy_communities_crm/config.py
odoo/addons/energy_communities_crm/controllers/__init__.py
odoo/addons/energy_communities_crm/controllers/crm_api_controller.py
odoo/addons/energy_communities_crm/controllers/website_community_data.py
odoo/addons/energy_communities_crm/data/mail_template_data.xml
odoo/addons/energy_communities_crm/demo/crm_lead_demo.xml
odoo/addons/energy_communities_crm/demo/crm_lead_metadata_mapping_demo.xml
odoo/addons/energy_communities_crm/i18n/ca_ES.po
odoo/addons/energy_communities_crm/i18n/energy_communities_crm.pot
odoo/addons/energy_communities_crm/i18n/es.po
odoo/addons/energy_communities_crm/i18n/eu_ES.po
odoo/addons/energy_communities_crm/models/__init__.py
odoo/addons/energy_communities_crm/models/crm_lead.py
odoo/addons/energy_communities_crm/models/crm_lead_metadata_line.py
odoo/addons/energy_communities_crm/models/crm_lead_metadata_mapping.py
odoo/addons/energy_communities_crm/models/crm_lead_metadata_mapping_field.py
odoo/addons/energy_communities_crm/models/crm_stage.py
odoo/addons/energy_communities_crm/models/crm_tag.py
odoo/addons/energy_communities_crm/models/crm_team.py
odoo/addons/energy_communities_crm/models/utm_source.py
odoo/addons/energy_communities_crm/security/ir.model.access.csv
odoo/addons/energy_communities_crm/security/ir_rule_data.xml
odoo/addons/energy_communities_crm/security/res_users_role_data.xml
odoo/addons/energy_communities_crm/services/__init__.py
odoo/addons/energy_communities_crm/services/crm_lead_service.py
odoo/addons/energy_communities_crm/static/src/js/community-data-website.js
odoo/addons/energy_communities_crm/tests/__init__.py
odoo/addons/energy_communities_crm/tests/test_baserest_crm_lead_service.py
odoo/addons/energy_communities_crm/tests/test_crm_lead_service.py
odoo/addons/energy_communities_crm/tests/testing_cases.py
odoo_addon_energy_communities_crm-16.0.0.3.3.dist-info/METADATA
odoo_addon_energy_communities_crm-16.0.0.3.3.dist-info/WHEEL
odoo_addon_energy_communities_crm-16.0.0.3.3.dist-info/top_level.txt
odoo_addon_energy_communities_crm-16.0.0.3.3.dist-info/RECORD
