Metadata-Version: 2.1
Name: odoo-addon-energy_communities_crm
Version: 16.0.0.3.3
Requires-Python: >=3.10
Requires-Dist: odoo-addon-crm_metadata>=16.0dev,<16.1dev
Requires-Dist: odoo-addon-crm_metadata_rest_api>=16.0dev,<16.1dev
Requires-Dist: odoo-addon-crm_rest_api>=16.0dev,<16.1dev
Requires-Dist: odoo-addon-energy_communities>=16.0dev,<16.1dev
Requires-Dist: odoo>=16.0a,<16.1dev
Summary: Use CRM for coordinators and energy communities
Home-page: https://git.coopdevs.org/coopdevs/comunitats-energetiques/odoo-ce
License: AGPL-3
Author: Som Comunitats
Classifier: Programming Language :: Python
Classifier: Framework :: Odoo
Classifier: Framework :: Odoo :: 16.0
Classifier: License :: OSI Approved :: GNU Affero General Public License v3
